colorizedtextconsole/__init__.py
colorizedtextconsole/consolecolor.py
colorizedtextconsole-0.0.1.dist-info/METADATA
colorizedtextconsole-0.0.1.dist-info/WHEEL
colorizedtextconsole-0.0.1.dist-info/top_level.txt
colorizedtextconsole-0.0.1.dist-info/RECORD
