Metadata-Version: 2.1
Name: colorizedtextconsole
Version: 0.0.1
Summary: Colorized text console
Author: CeREF Technique
Author-email: licence.tech@ceref.be
Keywords: python,Colorized text console
Classifier: Development Status :: 3 - Alpha
Classifier: Intended Audience :: Education
Classifier: Programming Language :: Python :: 2
Classifier: Programming Language :: Python :: 3
Classifier: Operating System :: MacOS :: MacOS X
Classifier: Operating System :: Microsoft :: Windows
